liftero_test_package/Datafile.py
liftero_test_package/Dataset.py
liftero_test_package/HLAPI.py
liftero_test_package/LAPI.py
liftero_test_package/Plotting.py
liftero_test_package/__init__.py
liftero_test_package/plot_1.py
liftero_test_package/plot_2.py
liftero_test_package/plot_3.py
liftero_test_package-0.17.dist-info/METADATA
liftero_test_package-0.17.dist-info/WHEEL
liftero_test_package-0.17.dist-info/top_level.txt
liftero_test_package-0.17.dist-info/RECORD
